htmf_format/__init__.py
htmf_format/__main__.py
htmf_format/astcheck.py
htmf_format/beautifiers.py
htmf_format/clicky.py
htmf_format/files.py
htmf_format/formatter.py
htmf_format/output.py
htmf_format/report.py
htmf_format/utils.py
htmf_format/_vendor/readme.md
htmf_format/_vendor/htmlbeautifier/__init__.py
htmf_format/_vendor/htmlbeautifier/core/__init__.py
htmf_format/_vendor/htmlbeautifier/core/directives.py
htmf_format/_vendor/htmlbeautifier/core/inputscanner.py
htmf_format/_vendor/htmlbeautifier/core/options.py
htmf_format/_vendor/htmlbeautifier/core/output.py
htmf_format/_vendor/htmlbeautifier/core/pattern.py
htmf_format/_vendor/htmlbeautifier/core/templatablepattern.py
htmf_format/_vendor/htmlbeautifier/core/token.py
htmf_format/_vendor/htmlbeautifier/core/tokenizer.py
htmf_format/_vendor/htmlbeautifier/core/tokenstream.py
htmf_format/_vendor/htmlbeautifier/core/whitespacepattern.py
htmf_format/_vendor/htmlbeautifier/html/__init__.py
htmf_format/_vendor/htmlbeautifier/html/beautifier.py
htmf_format/_vendor/htmlbeautifier/html/options.py
htmf_format/_vendor/htmlbeautifier/html/tokenizer.py
htmf_format-0.1.1.dist-info/entry_points.txt
htmf_format-0.1.1.dist-info/LICENSE
htmf_format-0.1.1.dist-info/WHEEL
htmf_format-0.1.1.dist-info/METADATA
htmf_format-0.1.1.dist-info/RECORD
